hey/__init__.py
hey/docx.py
heyWFeng/__init__.py
heyWFeng/docx.py
heyWFeng/test.py
service/__init__.py
service/test_service.py
PyOfficeFile-0.0.1.dist-info/LICENSE
PyOfficeFile-0.0.1.dist-info/METADATA
PyOfficeFile-0.0.1.dist-info/WHEEL
PyOfficeFile-0.0.1.dist-info/top_level.txt
PyOfficeFile-0.0.1.dist-info/RECORD
